cocodev/django/deployment_configuration/__init__.py
cocodev/django/deployment_configuration/admin.py
cocodev/django/deployment_configuration/apps.py
cocodev/django/deployment_configuration/asynchronous.py
cocodev/django/deployment_configuration/core.py
cocodev/django/deployment_configuration/data.py
cocodev/django/deployment_configuration/deployment_settings.py
cocodev/django/deployment_configuration/django_cache_helpers.py
cocodev/django/deployment_configuration/django_settings_helpers.py
cocodev/django/deployment_configuration/exceptions.py
cocodev/django/deployment_configuration/import_helper.py
cocodev/django/deployment_configuration/load.py
cocodev/django/deployment_configuration/magic.py
cocodev/django/deployment_configuration/metadata.py
cocodev/django/deployment_configuration/models.py
cocodev/django/deployment_configuration/retrieve.py
cocodev/django/deployment_configuration/shortcuts.py
cocodev/django/deployment_configuration/signals.py
cocodev/django/deployment_configuration/store.py
cocodev/django/deployment_configuration/typing.py
cocodev/django/deployment_configuration/migrations/0001_initial.py
cocodev/django/deployment_configuration/migrations/0002_rename_value_option_raw_value.py
cocodev/django/deployment_configuration/migrations/0003_alter_option_supported_types.py
cocodev/django/deployment_configuration/migrations/0004_alter_option_default_value_change_behavior.py
cocodev/django/deployment_configuration/migrations/__init__.py
cocodev/django/deployment_configuration/static/deployment_configuration/admin_live_update.js
django_easy_configuration-1.0.7.dist-info/LICENSE.txt
django_easy_configuration-1.0.7.dist-info/METADATA
django_easy_configuration-1.0.7.dist-info/WHEEL
django_easy_configuration-1.0.7.dist-info/top_level.txt
django_easy_configuration-1.0.7.dist-info/RECORD
