Metadata-Version: 2.1
Name: django-easy-configuration
Version: 1.0.7
Summary: Quick and easy configuration of a deployment through Django Admin!
Home-page: https://github.com/cocodev/django_easy_configuration/
Author: MrCocoDev
Author-email: 3229549+cocodev@users.noreply.github.com
License: MIT
Project-URL: Documentation, https://github.com/cocodev/django_easy_configuration/
Platform: any
Classifier: Development Status :: 4 - Beta
Classifier: Programming Language :: Python
License-File: LICENSE.txt
Requires-Dist: django
Requires-Dist: importlib-metadata ; python_version < "3.8"
Provides-Extra: testing
Requires-Dist: setuptools ; extra == 'testing'
Requires-Dist: pytest ; extra == 'testing'
Requires-Dist: pytest-cov ; extra == 'testing'
Requires-Dist: pytest-django ; extra == 'testing'
Requires-Dist: pytest-random-order ; extra == 'testing'
